okstdio/__init__.py
okstdio/client/__init__.py
okstdio/client/application.py
okstdio/general/__init__.py
okstdio/general/errors.py
okstdio/general/jsonrpc_model.py
okstdio/py.typed
okstdio/server/__init__.py
okstdio/server/appdoc.py
okstdio/server/application.py
okstdio/server/middleware.py
okstdio/server/router.py
okstdio/server/stream.py
okstdio-0.1.0.dist-info/WHEEL
okstdio-0.1.0.dist-info/METADATA
okstdio-0.1.0.dist-info/RECORD
