Metadata-Version: 2.3
Name: okstdio
Version: 0.1.0
Summary: 基于 Stdio 的 JSON RPC 父子进程通信模块
Keywords: jsonrpc,stdio,rpc,ipc,subprocess,asyncio
Author: jianjian
Author-email: jianjian <jianjian2048@gmail.com>
License: MIT
Classifier: Development Status :: 3 - Alpha
Classifier: Intended Audience :: Developers
Classifier: License :: OSI Approved :: MIT License
Classifier: Programming Language :: Python :: 3
Classifier: Programming Language :: Python :: 3.10
Classifier: Programming Language :: Python :: 3.11
Classifier: Programming Language :: Python :: 3.12
Classifier: Topic :: Software Development :: Libraries :: Python Modules
Classifier: Topic :: System :: Networking
Requires-Dist: pydantic>=2.12.4
Requires-Python: >=3.10
